subforms/__init__.py
subforms/apps.py
subforms/fields.py
subforms/py.typed
subforms/static/css/subforms.css
subforms/static/js/subforms.js
subforms/templates/subforms/array.html
subforms/templates/subforms/nested.html
subforms/widgets.py
django_subforms-0.4.1.dist-info/LICENSE
django_subforms-0.4.1.dist-info/METADATA
django_subforms-0.4.1.dist-info/WHEEL
django_subforms-0.4.1.dist-info/RECORD
