Metadata-Version: 2.3
Name: django-subforms
Version: 0.4.1
Summary: Wrap django forms as fields and fields as dynamic arrays.
License: MIT
Keywords: django,sub,form,nested,widget,json,array,dynamic
Author: Matti Lamppu
Author-email: lamppu.matti.akseli@gmail.com
Requires-Python: >=3.11,<4
Classifier: Environment :: Web Environment
Classifier: Operating System :: OS Independent
Classifier: Programming Language :: Python
Classifier: Programming Language :: Python :: 3
Classifier: Programming Language :: Python :: 3 :: Only
Classifier: Programming Language :: Python :: 3.11
Classifier: Programming Language :: Python :: 3.12
Classifier: Programming Language :: Python :: 3.13
Classifier: Framework :: Django :: 4.2
Classifier: Framework :: Django :: 5.0
Classifier: Framework :: Django :: 5.1
Classifier: Framework :: Django :: 5.2
Classifier: Intended Audience :: Developers
Classifier: Natural Language :: English
Requires-Dist: Django (>=4.2)
Project-URL: Bug Tracker, https://github.com/MrThearMan/django-subforms/issues
Project-URL: Documentation, https://mrthearman.github.io/django-subforms
Project-URL: Homepage, https://mrthearman.github.io/django-subforms
Project-URL: Repository, https://github.com/MrThearMan/django-subforms
